rest_assured/__init__.py
rest_assured/testcases.py
rest_assured/contrib/__init__.py
rest_assured/contrib/drf_fsm_transitions.py
tests/__init__.py
tests/conftest.py
tests/mocks.py
tests/models.py
tests/test_base.py
tests/test_create.py
tests/test_destroy.py
tests/test_detail.py
tests/test_list.py
tests/test_update.py
tests/urls.py
django_rest_assured-0.2.3.dist-info/AUTHORS.rst
django_rest_assured-0.2.3.dist-info/LICENSE
django_rest_assured-0.2.3.dist-info/METADATA
django_rest_assured-0.2.3.dist-info/WHEEL
django_rest_assured-0.2.3.dist-info/top_level.txt
django_rest_assured-0.2.3.dist-info/RECORD
