Metadata-Version: 2.1
Name: django-rest-assured
Version: 0.2.3
Summary: Django REST Assured instantly test-covers your Django REST Framework based API.
Home-page: https://github.com/ydaniv/django-rest-assured
Author: Yehonatan Daniv
Author-email: maggotfish@gmail.com
License: BSD
Platform: UNKNOWN
Classifier: Development Status :: 5 - Production/Stable
Classifier: Environment :: Web Environment
Classifier: Framework :: Django
Classifier: Intended Audience :: Developers
Classifier: License :: OSI Approved :: BSD License
Classifier: Operating System :: OS Independent
Classifier: Programming Language :: Python
Classifier: Programming Language :: Python :: 3
Classifier: Topic :: Internet :: WWW/HTTP
Requires-Dist: django (>=1.6)
Requires-Dist: djangorestframework (>=2.4.3)
Requires-Dist: six
